pydms_config_server/__init__.py
pydms_config_server/config.py
pydms_config_server/manager.py
pydms_config_server/server.py
pydms_config_server/utils.py
pydms_config_server/data/static/alertify.min.css
pydms_config_server/data/static/alertify.min.js
pydms_config_server/data/static/bootstrap.min.css
pydms_config_server/data/static/bootstrap.min.js
pydms_config_server/data/static/jquery.jgrowl.min.js
pydms_config_server/data/static/jquery.min.js
pydms_config_server/data/static/jsonform.js
pydms_config_server/data/static/jsv.js
pydms_config_server/data/static/manage.js
pydms_config_server/data/static/popper.min.js
pydms_config_server/data/static/underscore.js
pydms_config_server/data/templates/manage.html
pydms_config_server-0.0.0.4.dist-info/LICENSE
pydms_config_server-0.0.0.4.dist-info/METADATA
pydms_config_server-0.0.0.4.dist-info/WHEEL
pydms_config_server-0.0.0.4.dist-info/entry_points.txt
pydms_config_server-0.0.0.4.dist-info/top_level.txt
pydms_config_server-0.0.0.4.dist-info/RECORD
