Metadata-Version: 2.1
Name: pydms-config-server
Version: 0.0.0.4
Summary: pydms-config-server，config server of   microservice systems.
Home-page: http://github.com/Peiiii/pydms-config-server
Author: Wang Pei
Author-email: 1535376447@qq.com
License: UNKNOWN
Platform: UNKNOWN
Classifier: Programming Language :: Python :: 3
Classifier: License :: OSI Approved :: MIT License
Classifier: Operating System :: OS Independent
Requires-Python: >=3.0
Requires-Dist: sanic
Requires-Dist: jinja2
Requires-Dist: freehub
Requires-Dist: fire
